tc_core_analyzer_lib/__init__.py
tc_core_analyzer_lib/assess_engagement.py
tc_core_analyzer_lib/tests/__init__.py
tc_core_analyzer_lib/tests/integration/__init__.py
tc_core_analyzer_lib/tests/integration/test_active_members.py
tc_core_analyzer_lib/tests/integration/test_all_active_fourteen_period.py
tc_core_analyzer_lib/tests/integration/test_assess_mention.py
tc_core_analyzer_lib/tests/integration/test_assess_reactions.py
tc_core_analyzer_lib/tests/integration/test_assess_replies.py
tc_core_analyzer_lib/tests/integration/test_consistently_active.py
tc_core_analyzer_lib/tests/integration/test_disengaged_members.py
tc_core_analyzer_lib/tests/integration/test_disengaged_were_consistently_active.py
tc_core_analyzer_lib/tests/integration/test_disengaged_were_newly_active.py
tc_core_analyzer_lib/tests/integration/test_disengaged_were_vital.py
tc_core_analyzer_lib/tests/integration/test_lone_actions_all_active.py
tc_core_analyzer_lib/tests/integration/test_lone_thr_actions_active.py
tc_core_analyzer_lib/tests/integration/test_mention_active_members_from_int_matrix.py
tc_core_analyzer_lib/tests/integration/test_newly_active_continuous_period.py
tc_core_analyzer_lib/tests/integration/test_newly_active_discontinued_period.py
tc_core_analyzer_lib/tests/integration/test_non_consistently_active.py
tc_core_analyzer_lib/tests/integration/test_partially_consistently_active.py
tc_core_analyzer_lib/tests/integration/test_still_active.py
tc_core_analyzer_lib/tests/integration/test_thr_actions_all_active.py
tc_core_analyzer_lib/tests/integration/test_vital.py
tc_core_analyzer_lib/tests/unit/__init__.py
tc_core_analyzer_lib/tests/unit/test_assess_active.py
tc_core_analyzer_lib/tests/unit/test_assess_connected.py
tc_core_analyzer_lib/tests/unit/test_assess_consistent.py
tc_core_analyzer_lib/tests/unit/test_assess_dropped.py
tc_core_analyzer_lib/tests/unit/test_assess_lurker.py
tc_core_analyzer_lib/tests/unit/test_assess_overlap.py
tc_core_analyzer_lib-1.3.1.dist-info/METADATA
tc_core_analyzer_lib-1.3.1.dist-info/WHEEL
tc_core_analyzer_lib-1.3.1.dist-info/top_level.txt
tc_core_analyzer_lib-1.3.1.dist-info/RECORD
