Metadata-Version: 2.1
Name: tc-core-analyzer-lib
Version: 1.3.1
Summary: TogetherCrew core analyzer library.
Author: Mohammad Amin Dadgar, TogetherCrew
Maintainer: Mohammad Amin Dadgar
Maintainer-email: dadgaramin96@gmail.com
Requires-Dist: numpy ==1.24.1
Requires-Dist: pytest ==7.2.0
Requires-Dist: pytest-cov ==4.0.0
Requires-Dist: coverage ==7.2.5
Requires-Dist: python-dotenv >=1.0.0
Requires-Dist: networkx ==3.1
